README.md
setup.py
cliff/__init__.py
cliff/api.py
cliff/test.py
mediacloud_cliff.egg-info/PKG-INFO
mediacloud_cliff.egg-info/SOURCES.txt
mediacloud_cliff.egg-info/dependency_links.txt
mediacloud_cliff.egg-info/not-zip-safe
mediacloud_cliff.egg-info/requires.txt
mediacloud_cliff.egg-info/top_level.txt