Metadata-Version: 2.1
Name: mediacloud-cliff
Version: 2.6.0
Summary: Media Cloud CLIFF API Client Library
Home-page: http://cliff.mediacloud.org
Author: Rahul Bhargava
Author-email: rahulb@media.mit.edu
License: MIT
Platform: UNKNOWN
